aes_gcm_rsa_oaep/__init__.py
aes_gcm_rsa_oaep/types.py
aes_gcm_rsa_oaep-0.1.0.dist-info/LICENSE
aes_gcm_rsa_oaep-0.1.0.dist-info/WHEEL
aes_gcm_rsa_oaep-0.1.0.dist-info/METADATA
aes_gcm_rsa_oaep-0.1.0.dist-info/RECORD
